odoo/addons/stock_picking_report_line_product_without_internal_ref/README.rst
odoo/addons/stock_picking_report_line_product_without_internal_ref/__manifest__.py
odoo/addons/stock_picking_report_line_product_without_internal_ref/reports/report_deliveryslip.xml
odoo/addons/stock_picking_report_line_product_without_internal_ref/static/description/icon.png
odoo_addon_stock_picking_report_line_product_without_internal_ref-15.0.1.0.0.1.dist-info/METADATA
odoo_addon_stock_picking_report_line_product_without_internal_ref-15.0.1.0.0.1.dist-info/WHEEL
odoo_addon_stock_picking_report_line_product_without_internal_ref-15.0.1.0.0.1.dist-info/top_level.txt
odoo_addon_stock_picking_report_line_product_without_internal_ref-15.0.1.0.0.1.dist-info/RECORD
