Metadata-Version: 2.1
Name: odoo-addon-stock_picking_report_line_product_without_internal_ref
Version: 15.0.1.0.0.1
Summary: Stock Picking Report Line Product Without Internal Reference
Home-page: https://github.com/sygel-technology/sy-stock-logistics-workflow
Author: Sygel, Odoo Community Association (OCA)
Author-email: support@odoo-community.org
License: AGPL-3
Classifier: Programming Language :: Python
Classifier: Framework :: Odoo
Classifier: Framework :: Odoo :: 15.0
Classifier: License :: OSI Approved :: GNU Affero General Public License v3
Requires-Python: >=3.8
Requires-Dist: odoo<15.1dev,>=15.0a
